jin_utils/__init__.py
jin_utils/colors.py
jin_utils/decorators.py
jin_utils/io.py
jin_utils/matrix.py
jin_utils/misc.py
jin_utils/rpy2_utils.py
jin_utils/version.py
jin_utils-0.4.1.dist-info/LICENSE
jin_utils-0.4.1.dist-info/METADATA
jin_utils-0.4.1.dist-info/WHEEL
jin_utils-0.4.1.dist-info/top_level.txt
jin_utils-0.4.1.dist-info/RECORD
