Metadata-Version: 2.1
Name: jin-utils
Version: 0.4.1
Summary: The package contains some useful functions for my daily work
Author: Huaqing Jin
Author-email: kevinjin0423@gmail.com
License-File: LICENSE
Requires-Dist: numpy >=1.18.0
Requires-Dist: pandas >=1.0.0
Requires-Dist: easydict
Requires-Dist: matplotlib
Requires-Dist: rpy2
Requires-Dist: pyyaml
